mlkem/__init__.py
mlkem/data_types.py
mlkem/fast_k_pke.py
mlkem/fastmath.cp311-win_amd64.pyd
mlkem/k_pke.py
mlkem/ml_kem.py
mlkem/parameter_set.py
mlkem/auxiliary/__init__.py
mlkem/auxiliary/crypto.py
mlkem/auxiliary/general.py
mlkem/auxiliary/ntt.py
mlkem/auxiliary/sampling.py
mlkem/math/__init__.py
mlkem/math/constants.py
mlkem/math/fastmathmodule.c
mlkem/math/field.py
mlkem/math/matrix.py
mlkem/math/polynomial_ring.py
mlkem-0.0.2.dist-info/METADATA
mlkem-0.0.2.dist-info/WHEEL
mlkem-0.0.2.dist-info/top_level.txt
mlkem-0.0.2.dist-info/RECORD
