Metadata-Version: 2.2
Name: mlkem
Version: 0.0.2
Summary: A module-latice-based key-encapsulation mechanism (ML-KEM). Implements the FIPS-203 standard.
Requires-Python: >=3.11
